m3u_manage/__init__.py
m3u_manage/__meta__.py
m3u_manage/clipboard.gif
m3u_manage/download.py
m3u_manage/filesystem.py
m3u_manage/gui.py
m3u_manage/gui2.py
m3u_manage/playlist.py
m3u_manage/tests.py
m3u_manage/util.py
m3u_manage/video.py
m3u_manage/commands/__init__.py
m3u_manage/commands/_dir.py
m3u_manage/commands/playlist.py
m3u_manage/commands/queue.py
m3u_manage-0.5.3.data/scripts/m3um
m3u_manage-0.5.3.dist-info/METADATA
m3u_manage-0.5.3.dist-info/WHEEL
m3u_manage-0.5.3.dist-info/top_level.txt
m3u_manage-0.5.3.dist-info/RECORD
