Metadata-Version: 2.1
Name: m3u-manage
Version: 0.5.3
Summary: Tools to create amd manage an m3u playlist
Home-page: https://m3u-manage.readthedocs.io
Author: Ian Dennis Miller
Author-email: ian@iandennismiller.com
License: MIT
Platform: UNKNOWN
Requires-Dist: click
Requires-Dist: m3u8
Requires-Dist: nltk
Requires-Dist: pygame
Requires-Dist: pymovie
Requires-Dist: getch
Requires-Dist: ffmpeg-python
Requires-Dist: ffmpeg-normalize
Requires-Dist: youtube-dl
